{
	"credit": "Made with Blockbench",
	"textures": {
		"0": "item/oc/withercharm",
		"particle": "item/oc/withercharm"
	},
	"elements": [
		{
			"name": "withercharm_0",
			"from": [7.33333, 7.83333, -1.83333],
			"to": [8.66667, 8.16667, 7.16667],
			"rotation": {"angle": 0, "axis": "y", "origin": [0, 7.83333, -2.16667]},
			"faces": {
				"north": {"uv": [8.66667, 0.33333, 7.33333, 0.66667], "texture": "#0"},
				"east": {"uv": [8.33333, 0.33333, 8.66667, 9.33333], "rotation": 90, "texture": "#0"},
				"south": {"uv": [7.33333, 9, 8.66667, 9.33333], "texture": "#0"},
				"west": {"uv": [7.33333, 0.33333, 7.66667, 9.33333], "rotation": 270, "texture": "#0"},
				"up": {"uv": [7.33333, 0.33333, 8.66667, 9.33333], "texture": "#0"},
				"down": {"uv": [7.33333, 9.33333, 8.66667, 0.33333], "texture": "#0"}
			}
		},
		{
			"name": "withercharm_1",
			"from": [5.66667, 7.83333, -1.5],
			"to": [7.33333, 8.16667, 7.83333],
			"rotation": {"angle": 0, "axis": "y", "origin": [0, 7.83333, -2.16667]},
			"faces": {
				"north": {"uv": [7.33333, 0.66667, 5.66667, 1], "texture": "#0"},
				"east": {"uv": [7, 0.66667, 7.33333, 10], "rotation": 90, "texture": "#0"},
				"south": {"uv": [5.66667, 9.66667, 7.33333, 10], "texture": "#0"},
				"west": {"uv": [5.66667, 0.66667, 6, 10], "rotation": 270, "texture": "#0"},
				"up": {"uv": [5.66667, 0.66667, 7.33333, 10], "texture": "#0"},
				"down": {"uv": [5.66667, 10, 7.33333, 0.66667], "texture": "#0"}
			}
		},
		{
			"name": "withercharm_2",
			"from": [8.66667, 7.83333, -1.5],
			"to": [10.33333, 8.16667, 7.16667],
			"rotation": {"angle": 0, "axis": "y", "origin": [0, 7.83333, -2.16667]},
			"faces": {
				"north": {"uv": [10.33333, 0.66667, 8.66667, 1], "texture": "#0"},
				"east": {"uv": [10, 0.66667, 10.33333, 9.33333], "rotation": 90, "texture": "#0"},
				"south": {"uv": [8.66667, 9, 10.33333, 9.33333], "texture": "#0"},
				"west": {"uv": [8.66667, 0.66667, 9, 9.33333], "rotation": 270, "texture": "#0"},
				"up": {"uv": [8.66667, 0.66667, 10.33333, 9.33333], "texture": "#0"},
				"down": {"uv": [8.66667, 9.33333, 10.33333, 0.66667], "texture": "#0"}
			}
		},
		{
			"name": "withercharm_3",
			"from": [4.66667, 7.83333, -1.16667],
			"to": [5.66667, 8.16667, 8.83333],
			"rotation": {"angle": 0, "axis": "y", "origin": [0, 7.83333, -2.16667]},
			"faces": {
				"north": {"uv": [5.66667, 1, 4.66667, 1.33333], "texture": "#0"},
				"east": {"uv": [5.33333, 1, 5.66667, 11], "rotation": 90, "texture": "#0"},
				"south": {"uv": [4.66667, 10.66667, 5.66667, 11], "texture": "#0"},
				"west": {"uv": [4.66667, 1, 5, 11], "rotation": 270, "texture": "#0"},
				"up": {"uv": [4.66667, 1, 5.66667, 11], "texture": "#0"},
				"down": {"uv": [4.66667, 11, 5.66667, 1], "texture": "#0"}
			}
		},
		{
			"name": "withercharm_4",
			"from": [10.33333, 7.83333, -1.16667],
			"to": [11.33333, 8.16667, 9.16667],
			"rotation": {"angle": 0, "axis": "y", "origin": [0, 7.83333, -2.16667]},
			"faces": {
				"north": {"uv": [11.33333, 1, 10.33333, 1.33333], "texture": "#0"},
				"east": {"uv": [11, 1, 11.33333, 11.33333], "rotation": 90, "texture": "#0"},
				"south": {"uv": [10.33333, 11, 11.33333, 11.33333], "texture": "#0"},
				"west": {"uv": [10.33333, 1, 10.66667, 11.33333], "rotation": 270, "texture": "#0"},
				"up": {"uv": [10.33333, 1, 11.33333, 11.33333], "texture": "#0"},
				"down": {"uv": [10.33333, 11.33333, 11.33333, 1], "texture": "#0"}
			}
		},
		{
			"name": "withercharm_5",
			"from": [4.33333, 7.83333, -0.83333],
			"to": [4.66667, 8.16667, 9.16667],
			"rotation": {"angle": 0, "axis": "y", "origin": [0, 7.83333, -2.16667]},
			"faces": {
				"north": {"uv": [4.66667, 1.33333, 4.33333, 1.66667], "texture": "#0"},
				"east": {"uv": [4.33333, 1.33333, 4.66667, 11.33333], "rotation": 90, "texture": "#0"},
				"south": {"uv": [4.33333, 11, 4.66667, 11.33333], "texture": "#0"},
				"west": {"uv": [4.33333, 1.33333, 4.66667, 11.33333], "rotation": 270, "texture": "#0"},
				"up": {"uv": [4.33333, 1.33333, 4.66667, 11.33333], "texture": "#0"},
				"down": {"uv": [4.33333, 11.33333, 4.66667, 1.33333], "texture": "#0"}
			}
		},
		{
			"name": "withercharm_6",
			"from": [11.33333, 7.83333, -0.83333],
			"to": [11.66667, 8.16667, 9.16667],
			"rotation": {"angle": 0, "axis": "y", "origin": [0, 7.83333, -2.16667]},
			"faces": {
				"north": {"uv": [11.66667, 1.33333, 11.33333, 1.66667], "texture": "#0"},
				"east": {"uv": [11.33333, 1.33333, 11.66667, 11.33333], "rotation": 90, "texture": "#0"},
				"south": {"uv": [11.33333, 11, 11.66667, 11.33333], "texture": "#0"},
				"west": {"uv": [11.33333, 1.33333, 11.66667, 11.33333], "rotation": 270, "texture": "#0"},
				"up": {"uv": [11.33333, 1.33333, 11.66667, 11.33333], "texture": "#0"},
				"down": {"uv": [11.33333, 11.33333, 11.66667, 1.33333], "texture": "#0"}
			}
		},
		{
			"name": "withercharm_7",
			"from": [3.66667, 7.83333, -0.5],
			"to": [4.33333, 8.16667, 8.83333],
			"rotation": {"angle": 0, "axis": "y", "origin": [0, 7.83333, -2.16667]},
			"faces": {
				"north": {"uv": [4.33333, 1.66667, 3.66667, 2], "texture": "#0"},
				"east": {"uv": [4, 1.66667, 4.33333, 11], "rotation": 90, "texture": "#0"},
				"south": {"uv": [3.66667, 10.66667, 4.33333, 11], "texture": "#0"},
				"west": {"uv": [3.66667, 1.66667, 4, 11], "rotation": 270, "texture": "#0"},
				"up": {"uv": [3.66667, 1.66667, 4.33333, 11], "texture": "#0"},
				"down": {"uv": [3.66667, 11, 4.33333, 1.66667], "texture": "#0"}
			}
		},
		{
			"name": "withercharm_8",
			"from": [11.66667, 7.83333, -0.5],
			"to": [12.33333, 8.16667, 8.83333],
			"rotation": {"angle": 0, "axis": "y", "origin": [0, 7.83333, -2.16667]},
			"faces": {
				"north": {"uv": [12.33333, 1.66667, 11.66667, 2], "texture": "#0"},
				"east": {"uv": [12, 1.66667, 12.33333, 11], "rotation": 90, "texture": "#0"},
				"south": {"uv": [11.66667, 10.66667, 12.33333, 11], "texture": "#0"},
				"west": {"uv": [11.66667, 1.66667, 12, 11], "rotation": 270, "texture": "#0"},
				"up": {"uv": [11.66667, 1.66667, 12.33333, 11], "texture": "#0"},
				"down": {"uv": [11.66667, 11, 12.33333, 1.66667], "texture": "#0"}
			}
		},
		{
			"name": "withercharm_9",
			"from": [3.33333, 7.83333, -0.16667],
			"to": [3.66667, 8.16667, 8.5],
			"rotation": {"angle": 0, "axis": "y", "origin": [0, 7.83333, -2.16667]},
			"faces": {
				"north": {"uv": [3.66667, 2, 3.33333, 2.33333], "texture": "#0"},
				"east": {"uv": [3.33333, 2, 3.66667, 10.66667], "rotation": 90, "texture": "#0"},
				"south": {"uv": [3.33333, 10.33333, 3.66667, 10.66667], "texture": "#0"},
				"west": {"uv": [3.33333, 2, 3.66667, 10.66667], "rotation": 270, "texture": "#0"},
				"up": {"uv": [3.33333, 2, 3.66667, 10.66667], "texture": "#0"},
				"down": {"uv": [3.33333, 10.66667, 3.66667, 2], "texture": "#0"}
			}
		},
		{
			"name": "withercharm_10",
			"from": [12.33333, 7.83333, -0.16667],
			"to": [12.66667, 8.16667, 8.83333],
			"rotation": {"angle": 0, "axis": "y", "origin": [0, 7.83333, -2.16667]},
			"faces": {
				"north": {"uv": [12.66667, 2, 12.33333, 2.33333], "texture": "#0"},
				"east": {"uv": [12.33333, 2, 12.66667, 11], "rotation": 90, "texture": "#0"},
				"south": {"uv": [12.33333, 10.66667, 12.66667, 11], "texture": "#0"},
				"west": {"uv": [12.33333, 2, 12.66667, 11], "rotation": 270, "texture": "#0"},
				"up": {"uv": [12.33333, 2, 12.66667, 11], "texture": "#0"},
				"down": {"uv": [12.33333, 11, 12.66667, 2], "texture": "#0"}
			}
		},
		{
			"name": "withercharm_11",
			"from": [3, 7.83333, 0.16667],
			"to": [3.33333, 8.16667, 8.5],
			"rotation": {"angle": 0, "axis": "y", "origin": [0, 7.83333, -2.16667]},
			"faces": {
				"north": {"uv": [3.33333, 2.33333, 3, 2.66667], "texture": "#0"},
				"east": {"uv": [3, 2.33333, 3.33333, 10.66667], "rotation": 90, "texture": "#0"},
				"south": {"uv": [3, 10.33333, 3.33333, 10.66667], "texture": "#0"},
				"west": {"uv": [3, 2.33333, 3.33333, 10.66667], "rotation": 270, "texture": "#0"},
				"up": {"uv": [3, 2.33333, 3.33333, 10.66667], "texture": "#0"},
				"down": {"uv": [3, 10.66667, 3.33333, 2.33333], "texture": "#0"}
			}
		},
		{
			"name": "withercharm_12",
			"from": [12.66667, 7.83333, 0.16667],
			"to": [13, 8.16667, 8.5],
			"rotation": {"angle": 0, "axis": "y", "origin": [0, 7.83333, -2.16667]},
			"faces": {
				"north": {"uv": [13, 2.33333, 12.66667, 2.66667], "texture": "#0"},
				"east": {"uv": [12.66667, 2.33333, 13, 10.66667], "rotation": 90, "texture": "#0"},
				"south": {"uv": [12.66667, 10.33333, 13, 10.66667], "texture": "#0"},
				"west": {"uv": [12.66667, 2.33333, 13, 10.66667], "rotation": 270, "texture": "#0"},
				"up": {"uv": [12.66667, 2.33333, 13, 10.66667], "texture": "#0"},
				"down": {"uv": [12.66667, 10.66667, 13, 2.33333], "texture": "#0"}
			}
		},
		{
			"name": "withercharm_13",
			"from": [2.66667, 7.83333, 0.5],
			"to": [3, 8.16667, 8.5],
			"rotation": {"angle": 0, "axis": "y", "origin": [0, 7.83333, -2.16667]},
			"faces": {
				"north": {"uv": [3, 2.66667, 2.66667, 3], "texture": "#0"},
				"east": {"uv": [2.66667, 2.66667, 3, 10.66667], "rotation": 90, "texture": "#0"},
				"south": {"uv": [2.66667, 10.33333, 3, 10.66667], "texture": "#0"},
				"west": {"uv": [2.66667, 2.66667, 3, 10.66667], "rotation": 270, "texture": "#0"},
				"up": {"uv": [2.66667, 2.66667, 3, 10.66667], "texture": "#0"},
				"down": {"uv": [2.66667, 10.66667, 3, 2.66667], "texture": "#0"}
			}
		},
		{
			"name": "withercharm_14",
			"from": [13, 7.83333, 0.5],
			"to": [13.33333, 8.16667, 8.16667],
			"rotation": {"angle": 0, "axis": "y", "origin": [0, 7.83333, -2.16667]},
			"faces": {
				"north": {"uv": [13.33333, 2.66667, 13, 3], "texture": "#0"},
				"east": {"uv": [13, 2.66667, 13.33333, 10.33333], "rotation": 90, "texture": "#0"},
				"south": {"uv": [13, 10, 13.33333, 10.33333], "texture": "#0"},
				"west": {"uv": [13, 2.66667, 13.33333, 10.33333], "rotation": 270, "texture": "#0"},
				"up": {"uv": [13, 2.66667, 13.33333, 10.33333], "texture": "#0"},
				"down": {"uv": [13, 10.33333, 13.33333, 2.66667], "texture": "#0"}
			}
		},
		{
			"name": "withercharm_15",
			"from": [2.33333, 7.83333, 0.83333],
			"to": [2.66667, 8.16667, 8.5],
			"rotation": {"angle": 0, "axis": "y", "origin": [0, 7.83333, -2.16667]},
			"faces": {
				"north": {"uv": [2.66667, 3, 2.33333, 3.33333], "texture": "#0"},
				"east": {"uv": [2.33333, 3, 2.66667, 10.66667], "rotation": 90, "texture": "#0"},
				"south": {"uv": [2.33333, 10.33333, 2.66667, 10.66667], "texture": "#0"},
				"west": {"uv": [2.33333, 3, 2.66667, 10.66667], "rotation": 270, "texture": "#0"},
				"up": {"uv": [2.33333, 3, 2.66667, 10.66667], "texture": "#0"},
				"down": {"uv": [2.33333, 10.66667, 2.66667, 3], "texture": "#0"}
			}
		},
		{
			"name": "withercharm_16",
			"from": [13.33333, 7.83333, 0.83333],
			"to": [13.66667, 8.16667, 8.16667],
			"rotation": {"angle": 0, "axis": "y", "origin": [0, 7.83333, -2.16667]},
			"faces": {
				"north": {"uv": [13.66667, 3, 13.33333, 3.33333], "texture": "#0"},
				"east": {"uv": [13.33333, 3, 13.66667, 10.33333], "rotation": 90, "texture": "#0"},
				"south": {"uv": [13.33333, 10, 13.66667, 10.33333], "texture": "#0"},
				"west": {"uv": [13.33333, 3, 13.66667, 10.33333], "rotation": 270, "texture": "#0"},
				"up": {"uv": [13.33333, 3, 13.66667, 10.33333], "texture": "#0"},
				"down": {"uv": [13.33333, 10.33333, 13.66667, 3], "texture": "#0"}
			}
		},
		{
			"name": "withercharm_17",
			"from": [2, 7.83333, 1.5],
			"to": [2.33333, 8.16667, 9.5],
			"rotation": {"angle": 0, "axis": "y", "origin": [0, 7.83333, -2.16667]},
			"faces": {
				"north": {"uv": [2.33333, 3.66667, 2, 4], "texture": "#0"},
				"east": {"uv": [2, 3.66667, 2.33333, 11.66667], "rotation": 90, "texture": "#0"},
				"south": {"uv": [2, 11.33333, 2.33333, 11.66667], "texture": "#0"},
				"west": {"uv": [2, 3.66667, 2.33333, 11.66667], "rotation": 270, "texture": "#0"},
				"up": {"uv": [2, 3.66667, 2.33333, 11.66667], "texture": "#0"},
				"down": {"uv": [2, 11.66667, 2.33333, 3.66667], "texture": "#0"}
			}
		},
		{
			"name": "withercharm_18",
			"from": [13.66667, 7.83333, 1.5],
			"to": [14, 8.16667, 7.83333],
			"rotation": {"angle": 0, "axis": "y", "origin": [0, 7.83333, -2.16667]},
			"faces": {
				"north": {"uv": [14, 3.66667, 13.66667, 4], "texture": "#0"},
				"east": {"uv": [13.66667, 3.66667, 14, 10], "rotation": 90, "texture": "#0"},
				"south": {"uv": [13.66667, 9.66667, 14, 10], "texture": "#0"},
				"west": {"uv": [13.66667, 3.66667, 14, 10], "rotation": 270, "texture": "#0"},
				"up": {"uv": [13.66667, 3.66667, 14, 10], "texture": "#0"},
				"down": {"uv": [13.66667, 10, 14, 3.66667], "texture": "#0"}
			}
		},
		{
			"name": "withercharm_19",
			"from": [1.66667, 7.83333, 1.83333],
			"to": [2, 8.16667, 9.16667],
			"rotation": {"angle": 0, "axis": "y", "origin": [0, 7.83333, -2.16667]},
			"faces": {
				"north": {"uv": [2, 4, 1.66667, 4.33333], "texture": "#0"},
				"east": {"uv": [1.66667, 4, 2, 11.33333], "rotation": 90, "texture": "#0"},
				"south": {"uv": [1.66667, 11, 2, 11.33333], "texture": "#0"},
				"west": {"uv": [1.66667, 4, 2, 11.33333], "rotation": 270, "texture": "#0"},
				"up": {"uv": [1.66667, 4, 2, 11.33333], "texture": "#0"},
				"down": {"uv": [1.66667, 11.33333, 2, 4], "texture": "#0"}
			}
		},
		{
			"name": "withercharm_20",
			"from": [14, 7.83333, 1.83333],
			"to": [14.33333, 8.16667, 7.83333],
			"rotation": {"angle": 0, "axis": "y", "origin": [0, 7.83333, -2.16667]},
			"faces": {
				"north": {"uv": [14.33333, 4, 14, 4.33333], "texture": "#0"},
				"east": {"uv": [14, 4, 14.33333, 10], "rotation": 90, "texture": "#0"},
				"south": {"uv": [14, 9.66667, 14.33333, 10], "texture": "#0"},
				"west": {"uv": [14, 4, 14.33333, 10], "rotation": 270, "texture": "#0"},
				"up": {"uv": [14, 4, 14.33333, 10], "texture": "#0"},
				"down": {"uv": [14, 10, 14.33333, 4], "texture": "#0"}
			}
		},
		{
			"name": "withercharm_21",
			"from": [1.33333, 7.83333, 2.16667],
			"to": [1.66667, 8.16667, 8.83333],
			"rotation": {"angle": 0, "axis": "y", "origin": [0, 7.83333, -2.16667]},
			"faces": {
				"north": {"uv": [1.66667, 4.33333, 1.33333, 4.66667], "texture": "#0"},
				"east": {"uv": [1.33333, 4.33333, 1.66667, 11], "rotation": 90, "texture": "#0"},
				"south": {"uv": [1.33333, 10.66667, 1.66667, 11], "texture": "#0"},
				"west": {"uv": [1.33333, 4.33333, 1.66667, 11], "rotation": 270, "texture": "#0"},
				"up": {"uv": [1.33333, 4.33333, 1.66667, 11], "texture": "#0"},
				"down": {"uv": [1.33333, 11, 1.66667, 4.33333], "texture": "#0"}
			}
		},
		{
			"name": "withercharm_22",
			"from": [14.33333, 7.83333, 2.16667],
			"to": [14.66667, 8.16667, 7.5],
			"rotation": {"angle": 0, "axis": "y", "origin": [0, 7.83333, -2.16667]},
			"faces": {
				"north": {"uv": [14.66667, 4.33333, 14.33333, 4.66667], "texture": "#0"},
				"east": {"uv": [14.33333, 4.33333, 14.66667, 9.66667], "rotation": 90, "texture": "#0"},
				"south": {"uv": [14.33333, 9.33333, 14.66667, 9.66667], "texture": "#0"},
				"west": {"uv": [14.33333, 4.33333, 14.66667, 9.66667], "rotation": 270, "texture": "#0"},
				"up": {"uv": [14.33333, 4.33333, 14.66667, 9.66667], "texture": "#0"},
				"down": {"uv": [14.33333, 9.66667, 14.66667, 4.33333], "texture": "#0"}
			}
		},
		{
			"name": "withercharm_23",
			"from": [1, 7.83333, 3.16667],
			"to": [1.33333, 8.16667, 7.83333],
			"rotation": {"angle": 0, "axis": "y", "origin": [0, 7.83333, -2.16667]},
			"faces": {
				"north": {"uv": [1.33333, 5.33333, 1, 5.66667], "texture": "#0"},
				"east": {"uv": [1, 5.33333, 1.33333, 10], "rotation": 90, "texture": "#0"},
				"south": {"uv": [1, 9.66667, 1.33333, 10], "texture": "#0"},
				"west": {"uv": [1, 5.33333, 1.33333, 10], "rotation": 270, "texture": "#0"},
				"up": {"uv": [1, 5.33333, 1.33333, 10], "texture": "#0"},
				"down": {"uv": [1, 10, 1.33333, 5.33333], "texture": "#0"}
			}
		},
		{
			"name": "withercharm_24",
			"from": [14.66667, 7.83333, 3.16667],
			"to": [15, 8.16667, 7.5],
			"rotation": {"angle": 0, "axis": "y", "origin": [0, 7.83333, -2.16667]},
			"faces": {
				"north": {"uv": [15, 5.33333, 14.66667, 5.66667], "texture": "#0"},
				"east": {"uv": [14.66667, 5.33333, 15, 9.66667], "rotation": 90, "texture": "#0"},
				"south": {"uv": [14.66667, 9.33333, 15, 9.66667], "texture": "#0"},
				"west": {"uv": [14.66667, 5.33333, 15, 9.66667], "rotation": 270, "texture": "#0"},
				"up": {"uv": [14.66667, 5.33333, 15, 9.66667], "texture": "#0"},
				"down": {"uv": [14.66667, 9.66667, 15, 5.33333], "texture": "#0"}
			}
		},
		{
			"name": "withercharm_25",
			"from": [0.66667, 7.83333, 4.83333],
			"to": [1, 8.16667, 6.16667],
			"rotation": {"angle": 0, "axis": "y", "origin": [0, 7.83333, -2.16667]},
			"faces": {
				"north": {"uv": [1, 7, 0.66667, 7.33333], "texture": "#0"},
				"east": {"uv": [0.66667, 7, 1, 8.33333], "rotation": 90, "texture": "#0"},
				"south": {"uv": [0.66667, 8, 1, 8.33333], "texture": "#0"},
				"west": {"uv": [0.66667, 7, 1, 8.33333], "rotation": 270, "texture": "#0"},
				"up": {"uv": [0.66667, 7, 1, 8.33333], "texture": "#0"},
				"down": {"uv": [0.66667, 8.33333, 1, 7], "texture": "#0"}
			}
		},
		{
			"name": "withercharm_26",
			"from": [15, 7.83333, 4.83333],
			"to": [15.33333, 8.16667, 6.16667],
			"rotation": {"angle": 0, "axis": "y", "origin": [0, 7.83333, -2.16667]},
			"faces": {
				"north": {"uv": [15.33333, 7, 15, 7.33333], "texture": "#0"},
				"east": {"uv": [15, 7, 15.33333, 8.33333], "rotation": 90, "texture": "#0"},
				"south": {"uv": [15, 8, 15.33333, 8.33333], "texture": "#0"},
				"west": {"uv": [15, 7, 15.33333, 8.33333], "rotation": 270, "texture": "#0"},
				"up": {"uv": [15, 7, 15.33333, 8.33333], "texture": "#0"},
				"down": {"uv": [15, 8.33333, 15.33333, 7], "texture": "#0"}
			}
		},
		{
			"name": "withercharm_27",
			"from": [7.33333, 7.83333, 7.16667],
			"to": [8.33333, 8.16667, 7.5],
			"rotation": {"angle": 0, "axis": "y", "origin": [0, 7.83333, -2.16667]},
			"faces": {
				"north": {"uv": [8.33333, 9.33333, 7.33333, 9.66667], "texture": "#0"},
				"east": {"uv": [8, 9.33333, 8.33333, 9.66667], "rotation": 90, "texture": "#0"},
				"south": {"uv": [7.33333, 9.33333, 8.33333, 9.66667], "texture": "#0"},
				"west": {"uv": [7.33333, 9.33333, 7.66667, 9.66667], "rotation": 270, "texture": "#0"},
				"up": {"uv": [7.33333, 9.33333, 8.33333, 9.66667], "texture": "#0"},
				"down": {"uv": [7.33333, 9.66667, 8.33333, 9.33333], "texture": "#0"}
			}
		},
		{
			"name": "withercharm_28",
			"from": [9, 7.83333, 7.16667],
			"to": [10.33333, 8.16667, 7.5],
			"rotation": {"angle": 0, "axis": "y", "origin": [0, 7.83333, -2.16667]},
			"faces": {
				"north": {"uv": [10.33333, 9.33333, 9, 9.66667], "texture": "#0"},
				"east": {"uv": [10, 9.33333, 10.33333, 9.66667], "rotation": 90, "texture": "#0"},
				"south": {"uv": [9, 9.33333, 10.33333, 9.66667], "texture": "#0"},
				"west": {"uv": [9, 9.33333, 9.33333, 9.66667], "rotation": 270, "texture": "#0"},
				"up": {"uv": [9, 9.33333, 10.33333, 9.66667], "texture": "#0"},
				"down": {"uv": [9, 9.66667, 10.33333, 9.33333], "texture": "#0"}
			}
		},
		{
			"name": "withercharm_29",
			"from": [7.33333, 7.83333, 7.5],
			"to": [7.66667, 8.16667, 7.83333],
			"rotation": {"angle": 0, "axis": "y", "origin": [0, 7.83333, -2.16667]},
			"faces": {
				"north": {"uv": [7.66667, 9.66667, 7.33333, 10], "texture": "#0"},
				"east": {"uv": [7.33333, 9.66667, 7.66667, 10], "rotation": 90, "texture": "#0"},
				"south": {"uv": [7.33333, 9.66667, 7.66667, 10], "texture": "#0"},
				"west": {"uv": [7.33333, 9.66667, 7.66667, 10], "rotation": 270, "texture": "#0"},
				"up": {"uv": [7.33333, 9.66667, 7.66667, 10], "texture": "#0"},
				"down": {"uv": [7.33333, 10, 7.66667, 9.66667], "texture": "#0"}
			}
		},
		{
			"name": "withercharm_30",
			"from": [9.33333, 7.83333, 7.5],
			"to": [10.33333, 8.16667, 8.16667],
			"rotation": {"angle": 0, "axis": "y", "origin": [0, 7.83333, -2.16667]},
			"faces": {
				"north": {"uv": [10.33333, 9.66667, 9.33333, 10], "texture": "#0"},
				"east": {"uv": [10, 9.66667, 10.33333, 10.33333], "rotation": 90, "texture": "#0"},
				"south": {"uv": [9.33333, 10, 10.33333, 10.33333], "texture": "#0"},
				"west": {"uv": [9.33333, 9.66667, 9.66667, 10.33333], "rotation": 270, "texture": "#0"},
				"up": {"uv": [9.33333, 9.66667, 10.33333, 10.33333], "texture": "#0"},
				"down": {"uv": [9.33333, 10.33333, 10.33333, 9.66667], "texture": "#0"}
			}
		},
		{
			"name": "withercharm_31",
			"from": [5.66667, 7.83333, 7.83333],
			"to": [6.66667, 8.16667, 8.83333],
			"rotation": {"angle": 0, "axis": "y", "origin": [0, 7.83333, -2.16667]},
			"faces": {
				"north": {"uv": [6.66667, 10, 5.66667, 10.33333], "texture": "#0"},
				"east": {"uv": [6.33333, 10, 6.66667, 11], "rotation": 90, "texture": "#0"},
				"south": {"uv": [5.66667, 10.66667, 6.66667, 11], "texture": "#0"},
				"west": {"uv": [5.66667, 10, 6, 11], "rotation": 270, "texture": "#0"},
				"up": {"uv": [5.66667, 10, 6.66667, 11], "texture": "#0"},
				"down": {"uv": [5.66667, 11, 6.66667, 10], "texture": "#0"}
			}
		},
		{
			"name": "withercharm_32",
			"from": [6.66667, 7.83333, 7.83333],
			"to": [7, 8.16667, 8.16667],
			"rotation": {"angle": 0, "axis": "y", "origin": [0, 7.83333, -2.16667]},
			"faces": {
				"north": {"uv": [7, 10, 6.66667, 10.33333], "texture": "#0"},
				"east": {"uv": [6.66667, 10, 7, 10.33333], "rotation": 90, "texture": "#0"},
				"south": {"uv": [6.66667, 10, 7, 10.33333], "texture": "#0"},
				"west": {"uv": [6.66667, 10, 7, 10.33333], "rotation": 270, "texture": "#0"},
				"up": {"uv": [6.66667, 10, 7, 10.33333], "texture": "#0"},
				"down": {"uv": [6.66667, 10.33333, 7, 10], "texture": "#0"}
			}
		},
		{
			"name": "withercharm_33",
			"from": [7.66667, 7.83333, 8.16667],
			"to": [8.66667, 8.16667, 9.5],
			"rotation": {"angle": 0, "axis": "y", "origin": [0, 7.83333, -2.16667]},
			"faces": {
				"north": {"uv": [8.66667, 10.33333, 7.66667, 10.66667], "texture": "#0"},
				"east": {"uv": [8.33333, 10.33333, 8.66667, 11.66667], "rotation": 90, "texture": "#0"},
				"south": {"uv": [7.66667, 11.33333, 8.66667, 11.66667], "texture": "#0"},
				"west": {"uv": [7.66667, 10.33333, 8, 11.66667], "rotation": 270, "texture": "#0"},
				"up": {"uv": [7.66667, 10.33333, 8.66667, 11.66667], "texture": "#0"},
				"down": {"uv": [7.66667, 11.66667, 8.66667, 10.33333], "texture": "#0"}
			}
		},
		{
			"name": "withercharm_34",
			"from": [9.66667, 7.83333, 8.16667],
			"to": [10.33333, 8.16667, 9.16667],
			"rotation": {"angle": 0, "axis": "y", "origin": [0, 7.83333, -2.16667]},
			"faces": {
				"north": {"uv": [10.33333, 10.33333, 9.66667, 10.66667], "texture": "#0"},
				"east": {"uv": [10, 10.33333, 10.33333, 11.33333], "rotation": 90, "texture": "#0"},
				"south": {"uv": [9.66667, 11, 10.33333, 11.33333], "texture": "#0"},
				"west": {"uv": [9.66667, 10.33333, 10, 11.33333], "rotation": 270, "texture": "#0"},
				"up": {"uv": [9.66667, 10.33333, 10.33333, 11.33333], "texture": "#0"},
				"down": {"uv": [9.66667, 11.33333, 10.33333, 10.33333], "texture": "#0"}
			}
		},
		{
			"name": "withercharm_35",
			"from": [7, 7.83333, 8.5],
			"to": [7.66667, 8.16667, 9.5],
			"rotation": {"angle": 0, "axis": "y", "origin": [0, 7.83333, -2.16667]},
			"faces": {
				"north": {"uv": [7.66667, 10.66667, 7, 11], "texture": "#0"},
				"east": {"uv": [7.33333, 10.66667, 7.66667, 11.66667], "rotation": 90, "texture": "#0"},
				"south": {"uv": [7, 11.33333, 7.66667, 11.66667], "texture": "#0"},
				"west": {"uv": [7, 10.66667, 7.33333, 11.66667], "rotation": 270, "texture": "#0"},
				"up": {"uv": [7, 10.66667, 7.66667, 11.66667], "texture": "#0"},
				"down": {"uv": [7, 11.66667, 7.66667, 10.66667], "texture": "#0"}
			}
		},
		{
			"name": "withercharm_36",
			"from": [2.33333, 7.83333, 8.83333],
			"to": [2.66667, 8.16667, 9.5],
			"rotation": {"angle": 0, "axis": "y", "origin": [0, 7.83333, -2.16667]},
			"faces": {
				"north": {"uv": [2.66667, 11, 2.33333, 11.33333], "texture": "#0"},
				"east": {"uv": [2.33333, 11, 2.66667, 11.66667], "rotation": 90, "texture": "#0"},
				"south": {"uv": [2.33333, 11.33333, 2.66667, 11.66667], "texture": "#0"},
				"west": {"uv": [2.33333, 11, 2.66667, 11.66667], "rotation": 270, "texture": "#0"},
				"up": {"uv": [2.33333, 11, 2.66667, 11.66667], "texture": "#0"},
				"down": {"uv": [2.33333, 11.66667, 2.66667, 11], "texture": "#0"}
			}
		},
		{
			"name": "withercharm_37",
			"from": [4, 7.83333, 8.83333],
			"to": [4.33333, 8.16667, 9.16667],
			"rotation": {"angle": 0, "axis": "y", "origin": [0, 7.83333, -2.16667]},
			"faces": {
				"north": {"uv": [4.33333, 11, 4, 11.33333], "texture": "#0"},
				"east": {"uv": [4, 11, 4.33333, 11.33333], "rotation": 90, "texture": "#0"},
				"south": {"uv": [4, 11, 4.33333, 11.33333], "texture": "#0"},
				"west": {"uv": [4, 11, 4.33333, 11.33333], "rotation": 270, "texture": "#0"},
				"up": {"uv": [4, 11, 4.33333, 11.33333], "texture": "#0"},
				"down": {"uv": [4, 11.33333, 4.33333, 11], "texture": "#0"}
			}
		},
		{
			"name": "withercharm_38",
			"from": [4.66667, 7.83333, 8.83333],
			"to": [5.33333, 8.16667, 9.16667],
			"rotation": {"angle": 0, "axis": "y", "origin": [0, 7.83333, -2.16667]},
			"faces": {
				"north": {"uv": [5.33333, 11, 4.66667, 11.33333], "texture": "#0"},
				"east": {"uv": [5, 11, 5.33333, 11.33333], "rotation": 90, "texture": "#0"},
				"south": {"uv": [4.66667, 11, 5.33333, 11.33333], "texture": "#0"},
				"west": {"uv": [4.66667, 11, 5, 11.33333], "rotation": 270, "texture": "#0"},
				"up": {"uv": [4.66667, 11, 5.33333, 11.33333], "texture": "#0"},
				"down": {"uv": [4.66667, 11.33333, 5.33333, 11], "texture": "#0"}
			}
		},
		{
			"name": "withercharm_39",
			"from": [6.66667, 7.83333, 8.83333],
			"to": [7, 8.16667, 9.16667],
			"rotation": {"angle": 0, "axis": "y", "origin": [0, 7.83333, -2.16667]},
			"faces": {
				"north": {"uv": [7, 11, 6.66667, 11.33333], "texture": "#0"},
				"east": {"uv": [6.66667, 11, 7, 11.33333], "rotation": 90, "texture": "#0"},
				"south": {"uv": [6.66667, 11, 7, 11.33333], "texture": "#0"},
				"west": {"uv": [6.66667, 11, 7, 11.33333], "rotation": 270, "texture": "#0"},
				"up": {"uv": [6.66667, 11, 7, 11.33333], "texture": "#0"},
				"down": {"uv": [6.66667, 11.33333, 7, 11], "texture": "#0"}
			}
		},
		{
			"name": "withercharm_40",
			"from": [8.66667, 7.83333, 8.83333],
			"to": [9, 8.16667, 9.83333],
			"rotation": {"angle": 0, "axis": "y", "origin": [0, 7.83333, -2.16667]},
			"faces": {
				"north": {"uv": [9, 11, 8.66667, 11.33333], "texture": "#0"},
				"east": {"uv": [8.66667, 11, 9, 12], "rotation": 90, "texture": "#0"},
				"south": {"uv": [8.66667, 11.66667, 9, 12], "texture": "#0"},
				"west": {"uv": [8.66667, 11, 9, 12], "rotation": 270, "texture": "#0"},
				"up": {"uv": [8.66667, 11, 9, 12], "texture": "#0"},
				"down": {"uv": [8.66667, 12, 9, 11], "texture": "#0"}
			}
		},
		{
			"name": "withercharm_41",
			"from": [14.66667, 7.83333, 8.83333],
			"to": [15.33333, 8.16667, 9.5],
			"rotation": {"angle": 0, "axis": "y", "origin": [0, 7.83333, -2.16667]},
			"faces": {
				"north": {"uv": [15.33333, 11, 14.66667, 11.33333], "texture": "#0"},
				"east": {"uv": [15, 11, 15.33333, 11.66667], "rotation": 90, "texture": "#0"},
				"south": {"uv": [14.66667, 11.33333, 15.33333, 11.66667], "texture": "#0"},
				"west": {"uv": [14.66667, 11, 15, 11.66667], "rotation": 270, "texture": "#0"},
				"up": {"uv": [14.66667, 11, 15.33333, 11.66667], "texture": "#0"},
				"down": {"uv": [14.66667, 11.66667, 15.33333, 11], "texture": "#0"}
			}
		},
		{
			"name": "withercharm_42",
			"from": [3, 7.83333, 9.16667],
			"to": [3.33333, 8.16667, 11.16667],
			"rotation": {"angle": 0, "axis": "y", "origin": [0, 7.83333, -2.16667]},
			"faces": {
				"north": {"uv": [3.33333, 11.33333, 3, 11.66667], "texture": "#0"},
				"east": {"uv": [3, 11.33333, 3.33333, 13.33333], "rotation": 90, "texture": "#0"},
				"south": {"uv": [3, 13, 3.33333, 13.33333], "texture": "#0"},
				"west": {"uv": [3, 11.33333, 3.33333, 13.33333], "rotation": 270, "texture": "#0"},
				"up": {"uv": [3, 11.33333, 3.33333, 13.33333], "texture": "#0"},
				"down": {"uv": [3, 13.33333, 3.33333, 11.33333], "texture": "#0"}
			}
		},
		{
			"name": "withercharm_43",
			"from": [4.66667, 7.83333, 9.16667],
			"to": [5, 8.16667, 9.5],
			"rotation": {"angle": 0, "axis": "y", "origin": [0, 7.83333, -2.16667]},
			"faces": {
				"north": {"uv": [5, 11.33333, 4.66667, 11.66667], "texture": "#0"},
				"east": {"uv": [4.66667, 11.33333, 5, 11.66667], "rotation": 90, "texture": "#0"},
				"south": {"uv": [4.66667, 11.33333, 5, 11.66667], "texture": "#0"},
				"west": {"uv": [4.66667, 11.33333, 5, 11.66667], "rotation": 270, "texture": "#0"},
				"up": {"uv": [4.66667, 11.33333, 5, 11.66667], "texture": "#0"},
				"down": {"uv": [4.66667, 11.66667, 5, 11.33333], "texture": "#0"}
			}
		},
		{
			"name": "withercharm_44",
			"from": [14, 7.83333, 9.16667],
			"to": [14.66667, 8.16667, 10.16667],
			"rotation": {"angle": 0, "axis": "y", "origin": [0, 7.83333, -2.16667]},
			"faces": {
				"north": {"uv": [14.66667, 11.33333, 14, 11.66667], "texture": "#0"},
				"east": {"uv": [14.33333, 11.33333, 14.66667, 12.33333], "rotation": 90, "texture": "#0"},
				"south": {"uv": [14, 12, 14.66667, 12.33333], "texture": "#0"},
				"west": {"uv": [14, 11.33333, 14.33333, 12.33333], "rotation": 270, "texture": "#0"},
				"up": {"uv": [14, 11.33333, 14.66667, 12.33333], "texture": "#0"},
				"down": {"uv": [14, 12.33333, 14.66667, 11.33333], "texture": "#0"}
			}
		},
		{
			"name": "withercharm_45",
			"from": [3.33333, 7.83333, 9.5],
			"to": [4, 8.16667, 10.83333],
			"rotation": {"angle": 0, "axis": "y", "origin": [0, 7.83333, -2.16667]},
			"faces": {
				"north": {"uv": [4, 11.66667, 3.33333, 12], "texture": "#0"},
				"east": {"uv": [3.66667, 11.66667, 4, 13], "rotation": 90, "texture": "#0"},
				"south": {"uv": [3.33333, 12.66667, 4, 13], "texture": "#0"},
				"west": {"uv": [3.33333, 11.66667, 3.66667, 13], "rotation": 270, "texture": "#0"},
				"up": {"uv": [3.33333, 11.66667, 4, 13], "texture": "#0"},
				"down": {"uv": [3.33333, 13, 4, 11.66667], "texture": "#0"}
			}
		},
		{
			"name": "withercharm_46",
			"from": [5.66667, 7.83333, 9.5],
			"to": [7, 8.16667, 10.83333],
			"rotation": {"angle": 0, "axis": "y", "origin": [0, 7.83333, -2.16667]},
			"faces": {
				"north": {"uv": [7, 11.66667, 5.66667, 12], "texture": "#0"},
				"east": {"uv": [6.66667, 11.66667, 7, 13], "rotation": 90, "texture": "#0"},
				"south": {"uv": [5.66667, 12.66667, 7, 13], "texture": "#0"},
				"west": {"uv": [5.66667, 11.66667, 6, 13], "rotation": 270, "texture": "#0"},
				"up": {"uv": [5.66667, 11.66667, 7, 13], "texture": "#0"},
				"down": {"uv": [5.66667, 13, 7, 11.66667], "texture": "#0"}
			}
		},
		{
			"name": "withercharm_47",
			"from": [9, 7.83333, 9.5],
			"to": [9.33333, 8.16667, 9.83333],
			"rotation": {"angle": 0, "axis": "y", "origin": [0, 7.83333, -2.16667]},
			"faces": {
				"north": {"uv": [9.33333, 11.66667, 9, 12], "texture": "#0"},
				"east": {"uv": [9, 11.66667, 9.33333, 12], "rotation": 90, "texture": "#0"},
				"south": {"uv": [9, 11.66667, 9.33333, 12], "texture": "#0"},
				"west": {"uv": [9, 11.66667, 9.33333, 12], "rotation": 270, "texture": "#0"},
				"up": {"uv": [9, 11.66667, 9.33333, 12], "texture": "#0"},
				"down": {"uv": [9, 12, 9.33333, 11.66667], "texture": "#0"}
			}
		},
		{
			"name": "withercharm_48",
			"from": [10, 7.83333, 9.5],
			"to": [11, 8.16667, 10.83333],
			"rotation": {"angle": 0, "axis": "y", "origin": [0, 7.83333, -2.16667]},
			"faces": {
				"north": {"uv": [11, 11.66667, 10, 12], "texture": "#0"},
				"east": {"uv": [10.66667, 11.66667, 11, 13], "rotation": 90, "texture": "#0"},
				"south": {"uv": [10, 12.66667, 11, 13], "texture": "#0"},
				"west": {"uv": [10, 11.66667, 10.33333, 13], "rotation": 270, "texture": "#0"},
				"up": {"uv": [10, 11.66667, 11, 13], "texture": "#0"},
				"down": {"uv": [10, 13, 11, 11.66667], "texture": "#0"}
			}
		},
		{
			"name": "withercharm_49",
			"from": [14.66667, 7.83333, 9.5],
			"to": [15, 8.16667, 9.83333],
			"rotation": {"angle": 0, "axis": "y", "origin": [0, 7.83333, -2.16667]},
			"faces": {
				"north": {"uv": [15, 11.66667, 14.66667, 12], "texture": "#0"},
				"east": {"uv": [14.66667, 11.66667, 15, 12], "rotation": 90, "texture": "#0"},
				"south": {"uv": [14.66667, 11.66667, 15, 12], "texture": "#0"},
				"west": {"uv": [14.66667, 11.66667, 15, 12], "rotation": 270, "texture": "#0"},
				"up": {"uv": [14.66667, 11.66667, 15, 12], "texture": "#0"},
				"down": {"uv": [14.66667, 12, 15, 11.66667], "texture": "#0"}
			}
		},
		{
			"name": "withercharm_50",
			"from": [4, 7.83333, 9.83333],
			"to": [4.33333, 8.16667, 10.83333],
			"rotation": {"angle": 0, "axis": "y", "origin": [0, 7.83333, -2.16667]},
			"faces": {
				"north": {"uv": [4.33333, 12, 4, 12.33333], "texture": "#0"},
				"east": {"uv": [4, 12, 4.33333, 13], "rotation": 90, "texture": "#0"},
				"south": {"uv": [4, 12.66667, 4.33333, 13], "texture": "#0"},
				"west": {"uv": [4, 12, 4.33333, 13], "rotation": 270, "texture": "#0"},
				"up": {"uv": [4, 12, 4.33333, 13], "texture": "#0"},
				"down": {"uv": [4, 13, 4.33333, 12], "texture": "#0"}
			}
		},
		{
			"name": "withercharm_51",
			"from": [5.33333, 7.83333, 9.83333],
			"to": [5.66667, 8.16667, 11.16667],
			"rotation": {"angle": 0, "axis": "y", "origin": [0, 7.83333, -2.16667]},
			"faces": {
				"north": {"uv": [5.66667, 12, 5.33333, 12.33333], "texture": "#0"},
				"east": {"uv": [5.33333, 12, 5.66667, 13.33333], "rotation": 90, "texture": "#0"},
				"south": {"uv": [5.33333, 13, 5.66667, 13.33333], "texture": "#0"},
				"west": {"uv": [5.33333, 12, 5.66667, 13.33333], "rotation": 270, "texture": "#0"},
				"up": {"uv": [5.33333, 12, 5.66667, 13.33333], "texture": "#0"},
				"down": {"uv": [5.33333, 13.33333, 5.66667, 12], "texture": "#0"}
			}
		},
		{
			"name": "withercharm_52",
			"from": [7, 7.83333, 9.83333],
			"to": [8, 8.16667, 10.5],
			"rotation": {"angle": 0, "axis": "y", "origin": [0, 7.83333, -2.16667]},
			"faces": {
				"north": {"uv": [8, 12, 7, 12.33333], "texture": "#0"},
				"east": {"uv": [7.66667, 12, 8, 12.66667], "rotation": 90, "texture": "#0"},
				"south": {"uv": [7, 12.33333, 8, 12.66667], "texture": "#0"},
				"west": {"uv": [7, 12, 7.33333, 12.66667], "rotation": 270, "texture": "#0"},
				"up": {"uv": [7, 12, 8, 12.66667], "texture": "#0"},
				"down": {"uv": [7, 12.66667, 8, 12], "texture": "#0"}
			}
		},
		{
			"name": "withercharm_53",
			"from": [8, 7.83333, 9.83333],
			"to": [8.33333, 8.16667, 10.16667],
			"rotation": {"angle": 0, "axis": "y", "origin": [0, 7.83333, -2.16667]},
			"faces": {
				"north": {"uv": [8.33333, 12, 8, 12.33333], "texture": "#0"},
				"east": {"uv": [8, 12, 8.33333, 12.33333], "rotation": 90, "texture": "#0"},
				"south": {"uv": [8, 12, 8.33333, 12.33333], "texture": "#0"},
				"west": {"uv": [8, 12, 8.33333, 12.33333], "rotation": 270, "texture": "#0"},
				"up": {"uv": [8, 12, 8.33333, 12.33333], "texture": "#0"},
				"down": {"uv": [8, 12.33333, 8.33333, 12], "texture": "#0"}
			}
		},
		{
			"name": "withercharm_54",
			"from": [9.33333, 7.83333, 9.83333],
			"to": [10, 8.16667, 10.16667],
			"rotation": {"angle": 0, "axis": "y", "origin": [0, 7.83333, -2.16667]},
			"faces": {
				"north": {"uv": [10, 12, 9.33333, 12.33333], "texture": "#0"},
				"east": {"uv": [9.66667, 12, 10, 12.33333], "rotation": 90, "texture": "#0"},
				"south": {"uv": [9.33333, 12, 10, 12.33333], "texture": "#0"},
				"west": {"uv": [9.33333, 12, 9.66667, 12.33333], "rotation": 270, "texture": "#0"},
				"up": {"uv": [9.33333, 12, 10, 12.33333], "texture": "#0"},
				"down": {"uv": [9.33333, 12.33333, 10, 12], "texture": "#0"}
			}
		},
		{
			"name": "withercharm_55",
			"from": [12.33333, 7.83333, 9.83333],
			"to": [13.33333, 8.16667, 10.83333],
			"rotation": {"angle": 0, "axis": "y", "origin": [0, 7.83333, -2.16667]},
			"faces": {
				"north": {"uv": [13.33333, 12, 12.33333, 12.33333], "texture": "#0"},
				"east": {"uv": [13, 12, 13.33333, 13], "rotation": 90, "texture": "#0"},
				"south": {"uv": [12.33333, 12.66667, 13.33333, 13], "texture": "#0"},
				"west": {"uv": [12.33333, 12, 12.66667, 13], "rotation": 270, "texture": "#0"},
				"up": {"uv": [12.33333, 12, 13.33333, 13], "texture": "#0"},
				"down": {"uv": [12.33333, 13, 13.33333, 12], "texture": "#0"}
			}
		},
		{
			"name": "withercharm_56",
			"from": [2.66667, 7.83333, 10.16667],
			"to": [3, 8.16667, 10.83333],
			"rotation": {"angle": 0, "axis": "y", "origin": [0, 7.83333, -2.16667]},
			"faces": {
				"north": {"uv": [3, 12.33333, 2.66667, 12.66667], "texture": "#0"},
				"east": {"uv": [2.66667, 12.33333, 3, 13], "rotation": 90, "texture": "#0"},
				"south": {"uv": [2.66667, 12.66667, 3, 13], "texture": "#0"},
				"west": {"uv": [2.66667, 12.33333, 3, 13], "rotation": 270, "texture": "#0"},
				"up": {"uv": [2.66667, 12.33333, 3, 13], "texture": "#0"},
				"down": {"uv": [2.66667, 13, 3, 12.33333], "texture": "#0"}
			}
		},
		{
			"name": "withercharm_57",
			"from": [4.33333, 7.83333, 10.16667],
			"to": [4.66667, 8.16667, 10.5],
			"rotation": {"angle": 0, "axis": "y", "origin": [0, 7.83333, -2.16667]},
			"faces": {
				"north": {"uv": [4.66667, 12.33333, 4.33333, 12.66667], "texture": "#0"},
				"east": {"uv": [4.33333, 12.33333, 4.66667, 12.66667], "rotation": 90, "texture": "#0"},
				"south": {"uv": [4.33333, 12.33333, 4.66667, 12.66667], "texture": "#0"},
				"west": {"uv": [4.33333, 12.33333, 4.66667, 12.66667], "rotation": 270, "texture": "#0"},
				"up": {"uv": [4.33333, 12.33333, 4.66667, 12.66667], "texture": "#0"},
				"down": {"uv": [4.33333, 12.66667, 4.66667, 12.33333], "texture": "#0"}
			}
		},
		{
			"name": "withercharm_58",
			"from": [5, 7.83333, 10.16667],
			"to": [5.33333, 8.16667, 11.16667],
			"rotation": {"angle": 0, "axis": "y", "origin": [0, 7.83333, -2.16667]},
			"faces": {
				"north": {"uv": [5.33333, 12.33333, 5, 12.66667], "texture": "#0"},
				"east": {"uv": [5, 12.33333, 5.33333, 13.33333], "rotation": 90, "texture": "#0"},
				"south": {"uv": [5, 13, 5.33333, 13.33333], "texture": "#0"},
				"west": {"uv": [5, 12.33333, 5.33333, 13.33333], "rotation": 270, "texture": "#0"},
				"up": {"uv": [5, 12.33333, 5.33333, 13.33333], "texture": "#0"},
				"down": {"uv": [5, 13.33333, 5.33333, 12.33333], "texture": "#0"}
			}
		},
		{
			"name": "withercharm_59",
			"from": [9.66667, 7.83333, 10.16667],
			"to": [10, 8.16667, 10.5],
			"rotation": {"angle": 0, "axis": "y", "origin": [0, 7.83333, -2.16667]},
			"faces": {
				"north": {"uv": [10, 12.33333, 9.66667, 12.66667], "texture": "#0"},
				"east": {"uv": [9.66667, 12.33333, 10, 12.66667], "rotation": 90, "texture": "#0"},
				"south": {"uv": [9.66667, 12.33333, 10, 12.66667], "texture": "#0"},
				"west": {"uv": [9.66667, 12.33333, 10, 12.66667], "rotation": 270, "texture": "#0"},
				"up": {"uv": [9.66667, 12.33333, 10, 12.66667], "texture": "#0"},
				"down": {"uv": [9.66667, 12.66667, 10, 12.33333], "texture": "#0"}
			}
		},
		{
			"name": "withercharm_60",
			"from": [11.66667, 7.83333, 10.16667],
			"to": [12.33333, 8.16667, 10.83333],
			"rotation": {"angle": 0, "axis": "y", "origin": [0, 7.83333, -2.16667]},
			"faces": {
				"north": {"uv": [12.33333, 12.33333, 11.66667, 12.66667], "texture": "#0"},
				"east": {"uv": [12, 12.33333, 12.33333, 13], "rotation": 90, "texture": "#0"},
				"south": {"uv": [11.66667, 12.66667, 12.33333, 13], "texture": "#0"},
				"west": {"uv": [11.66667, 12.33333, 12, 13], "rotation": 270, "texture": "#0"},
				"up": {"uv": [11.66667, 12.33333, 12.33333, 13], "texture": "#0"},
				"down": {"uv": [11.66667, 13, 12.33333, 12.33333], "texture": "#0"}
			}
		},
		{
			"name": "withercharm_61",
			"from": [7, 7.83333, 10.5],
			"to": [7.33333, 8.16667, 10.83333],
			"rotation": {"angle": 0, "axis": "y", "origin": [0, 7.83333, -2.16667]},
			"faces": {
				"north": {"uv": [7.33333, 12.66667, 7, 13], "texture": "#0"},
				"east": {"uv": [7, 12.66667, 7.33333, 13], "rotation": 90, "texture": "#0"},
				"south": {"uv": [7, 12.66667, 7.33333, 13], "texture": "#0"},
				"west": {"uv": [7, 12.66667, 7.33333, 13], "rotation": 270, "texture": "#0"},
				"up": {"uv": [7, 12.66667, 7.33333, 13], "texture": "#0"},
				"down": {"uv": [7, 13, 7.33333, 12.66667], "texture": "#0"}
			}
		},
		{
			"name": "withercharm_62",
			"from": [8.33333, 7.83333, 10.5],
			"to": [9, 8.16667, 11.83333],
			"rotation": {"angle": 0, "axis": "y", "origin": [0, 7.83333, -2.16667]},
			"faces": {
				"north": {"uv": [9, 12.66667, 8.33333, 13], "texture": "#0"},
				"east": {"uv": [8.66667, 12.66667, 9, 14], "rotation": 90, "texture": "#0"},
				"south": {"uv": [8.33333, 13.66667, 9, 14], "texture": "#0"},
				"west": {"uv": [8.33333, 12.66667, 8.66667, 14], "rotation": 270, "texture": "#0"},
				"up": {"uv": [8.33333, 12.66667, 9, 14], "texture": "#0"},
				"down": {"uv": [8.33333, 14, 9, 12.66667], "texture": "#0"}
			}
		},
		{
			"name": "withercharm_63",
			"from": [11, 7.83333, 10.5],
			"to": [11.33333, 8.16667, 10.83333],
			"rotation": {"angle": 0, "axis": "y", "origin": [0, 7.83333, -2.16667]},
			"faces": {
				"north": {"uv": [11.33333, 12.66667, 11, 13], "texture": "#0"},
				"east": {"uv": [11, 12.66667, 11.33333, 13], "rotation": 90, "texture": "#0"},
				"south": {"uv": [11, 12.66667, 11.33333, 13], "texture": "#0"},
				"west": {"uv": [11, 12.66667, 11.33333, 13], "rotation": 270, "texture": "#0"},
				"up": {"uv": [11, 12.66667, 11.33333, 13], "texture": "#0"},
				"down": {"uv": [11, 13, 11.33333, 12.66667], "texture": "#0"}
			}
		},
		{
			"name": "withercharm_64",
			"from": [13.33333, 7.83333, 10.5],
			"to": [14, 8.16667, 10.83333],
			"rotation": {"angle": 0, "axis": "y", "origin": [0, 7.83333, -2.16667]},
			"faces": {
				"north": {"uv": [14, 12.66667, 13.33333, 13], "texture": "#0"},
				"east": {"uv": [13.66667, 12.66667, 14, 13], "rotation": 90, "texture": "#0"},
				"south": {"uv": [13.33333, 12.66667, 14, 13], "texture": "#0"},
				"west": {"uv": [13.33333, 12.66667, 13.66667, 13], "rotation": 270, "texture": "#0"},
				"up": {"uv": [13.33333, 12.66667, 14, 13], "texture": "#0"},
				"down": {"uv": [13.33333, 13, 14, 12.66667], "texture": "#0"}
			}
		},
		{
			"name": "withercharm_65",
			"from": [3.33333, 7.83333, 10.83333],
			"to": [3.66667, 8.16667, 11.16667],
			"rotation": {"angle": 0, "axis": "y", "origin": [0, 7.83333, -2.16667]},
			"faces": {
				"north": {"uv": [3.66667, 13, 3.33333, 13.33333], "texture": "#0"},
				"east": {"uv": [3.33333, 13, 3.66667, 13.33333], "rotation": 90, "texture": "#0"},
				"south": {"uv": [3.33333, 13, 3.66667, 13.33333], "texture": "#0"},
				"west": {"uv": [3.33333, 13, 3.66667, 13.33333], "rotation": 270, "texture": "#0"},
				"up": {"uv": [3.33333, 13, 3.66667, 13.33333], "texture": "#0"},
				"down": {"uv": [3.33333, 13.33333, 3.66667, 13], "texture": "#0"}
			}
		},
		{
			"name": "withercharm_66",
			"from": [5.66667, 7.83333, 10.83333],
			"to": [6, 8.16667, 11.16667],
			"rotation": {"angle": 0, "axis": "y", "origin": [0, 7.83333, -2.16667]},
			"faces": {
				"north": {"uv": [6, 13, 5.66667, 13.33333], "texture": "#0"},
				"east": {"uv": [5.66667, 13, 6, 13.33333], "rotation": 90, "texture": "#0"},
				"south": {"uv": [5.66667, 13, 6, 13.33333], "texture": "#0"},
				"west": {"uv": [5.66667, 13, 6, 13.33333], "rotation": 270, "texture": "#0"},
				"up": {"uv": [5.66667, 13, 6, 13.33333], "texture": "#0"},
				"down": {"uv": [5.66667, 13.33333, 6, 13], "texture": "#0"}
			}
		},
		{
			"name": "withercharm_67",
			"from": [8, 7.83333, 10.83333],
			"to": [8.33333, 8.16667, 12.5],
			"rotation": {"angle": 0, "axis": "y", "origin": [0, 7.83333, -2.16667]},
			"faces": {
				"north": {"uv": [8.33333, 13, 8, 13.33333], "texture": "#0"},
				"east": {"uv": [8, 13, 8.33333, 14.66667], "rotation": 90, "texture": "#0"},
				"south": {"uv": [8, 14.33333, 8.33333, 14.66667], "texture": "#0"},
				"west": {"uv": [8, 13, 8.33333, 14.66667], "rotation": 270, "texture": "#0"},
				"up": {"uv": [8, 13, 8.33333, 14.66667], "texture": "#0"},
				"down": {"uv": [8, 14.66667, 8.33333, 13], "texture": "#0"}
			}
		},
		{
			"name": "withercharm_68",
			"from": [9, 7.83333, 10.83333],
			"to": [9.33333, 8.16667, 11.83333],
			"rotation": {"angle": 0, "axis": "y", "origin": [0, 7.83333, -2.16667]},
			"faces": {
				"north": {"uv": [9.33333, 13, 9, 13.33333], "texture": "#0"},
				"east": {"uv": [9, 13, 9.33333, 14], "rotation": 90, "texture": "#0"},
				"south": {"uv": [9, 13.66667, 9.33333, 14], "texture": "#0"},
				"west": {"uv": [9, 13, 9.33333, 14], "rotation": 270, "texture": "#0"},
				"up": {"uv": [9, 13, 9.33333, 14], "texture": "#0"},
				"down": {"uv": [9, 14, 9.33333, 13], "texture": "#0"}
			}
		},
		{
			"name": "withercharm_69",
			"from": [12.66667, 7.83333, 10.83333],
			"to": [13.33333, 8.16667, 11.5],
			"rotation": {"angle": 0, "axis": "y", "origin": [0, 7.83333, -2.16667]},
			"faces": {
				"north": {"uv": [13.33333, 13, 12.66667, 13.33333], "texture": "#0"},
				"east": {"uv": [13, 13, 13.33333, 13.66667], "rotation": 90, "texture": "#0"},
				"south": {"uv": [12.66667, 13.33333, 13.33333, 13.66667], "texture": "#0"},
				"west": {"uv": [12.66667, 13, 13, 13.66667], "rotation": 270, "texture": "#0"},
				"up": {"uv": [12.66667, 13, 13.33333, 13.66667], "texture": "#0"},
				"down": {"uv": [12.66667, 13.66667, 13.33333, 13], "texture": "#0"}
			}
		},
		{
			"name": "withercharm_70",
			"from": [13.33333, 7.83333, 10.83333],
			"to": [13.66667, 8.16667, 11.16667],
			"rotation": {"angle": 0, "axis": "y", "origin": [0, 7.83333, -2.16667]},
			"faces": {
				"north": {"uv": [13.66667, 13, 13.33333, 13.33333], "texture": "#0"},
				"east": {"uv": [13.33333, 13, 13.66667, 13.33333], "rotation": 90, "texture": "#0"},
				"south": {"uv": [13.33333, 13, 13.66667, 13.33333], "texture": "#0"},
				"west": {"uv": [13.33333, 13, 13.66667, 13.33333], "rotation": 270, "texture": "#0"},
				"up": {"uv": [13.33333, 13, 13.66667, 13.33333], "texture": "#0"},
				"down": {"uv": [13.33333, 13.33333, 13.66667, 13], "texture": "#0"}
			}
		},
		{
			"name": "withercharm_71",
			"from": [7.66667, 7.83333, 11.16667],
			"to": [8, 8.16667, 12.83333],
			"rotation": {"angle": 0, "axis": "y", "origin": [0, 7.83333, -2.16667]},
			"faces": {
				"north": {"uv": [8, 13.33333, 7.66667, 13.66667], "texture": "#0"},
				"east": {"uv": [7.66667, 13.33333, 8, 15], "rotation": 90, "texture": "#0"},
				"south": {"uv": [7.66667, 14.66667, 8, 15], "texture": "#0"},
				"west": {"uv": [7.66667, 13.33333, 8, 15], "rotation": 270, "texture": "#0"},
				"up": {"uv": [7.66667, 13.33333, 8, 15], "texture": "#0"},
				"down": {"uv": [7.66667, 15, 8, 13.33333], "texture": "#0"}
			}
		},
		{
			"name": "withercharm_72",
			"from": [9.33333, 7.83333, 11.16667],
			"to": [9.66667, 8.16667, 11.5],
			"rotation": {"angle": 0, "axis": "y", "origin": [0, 7.83333, -2.16667]},
			"faces": {
				"north": {"uv": [9.66667, 13.33333, 9.33333, 13.66667], "texture": "#0"},
				"east": {"uv": [9.33333, 13.33333, 9.66667, 13.66667], "rotation": 90, "texture": "#0"},
				"south": {"uv": [9.33333, 13.33333, 9.66667, 13.66667], "texture": "#0"},
				"west": {"uv": [9.33333, 13.33333, 9.66667, 13.66667], "rotation": 270, "texture": "#0"},
				"up": {"uv": [9.33333, 13.33333, 9.66667, 13.66667], "texture": "#0"},
				"down": {"uv": [9.33333, 13.66667, 9.66667, 13.33333], "texture": "#0"}
			}
		},
		{
			"name": "withercharm_73",
			"from": [4, 7.83333, 11.5],
			"to": [4.66667, 8.16667, 12.16667],
			"rotation": {"angle": 0, "axis": "y", "origin": [0, 7.83333, -2.16667]},
			"faces": {
				"north": {"uv": [4.66667, 13.66667, 4, 14], "texture": "#0"},
				"east": {"uv": [4.33333, 13.66667, 4.66667, 14.33333], "rotation": 90, "texture": "#0"},
				"south": {"uv": [4, 14, 4.66667, 14.33333], "texture": "#0"},
				"west": {"uv": [4, 13.66667, 4.33333, 14.33333], "rotation": 270, "texture": "#0"},
				"up": {"uv": [4, 13.66667, 4.66667, 14.33333], "texture": "#0"},
				"down": {"uv": [4, 14.33333, 4.66667, 13.66667], "texture": "#0"}
			}
		},
		{
			"name": "withercharm_74",
			"from": [7.33333, 7.83333, 11.5],
			"to": [7.66667, 8.16667, 12.5],
			"rotation": {"angle": 0, "axis": "y", "origin": [0, 7.83333, -2.16667]},
			"faces": {
				"north": {"uv": [7.66667, 13.66667, 7.33333, 14], "texture": "#0"},
				"east": {"uv": [7.33333, 13.66667, 7.66667, 14.66667], "rotation": 90, "texture": "#0"},
				"south": {"uv": [7.33333, 14.33333, 7.66667, 14.66667], "texture": "#0"},
				"west": {"uv": [7.33333, 13.66667, 7.66667, 14.66667], "rotation": 270, "texture": "#0"},
				"up": {"uv": [7.33333, 13.66667, 7.66667, 14.66667], "texture": "#0"},
				"down": {"uv": [7.33333, 14.66667, 7.66667, 13.66667], "texture": "#0"}
			}
		},
		{
			"name": "withercharm_75",
			"from": [10.66667, 7.83333, 11.5],
			"to": [11.66667, 8.16667, 12.5],
			"rotation": {"angle": 0, "axis": "y", "origin": [0, 7.83333, -2.16667]},
			"faces": {
				"north": {"uv": [11.66667, 13.66667, 10.66667, 14], "texture": "#0"},
				"east": {"uv": [11.33333, 13.66667, 11.66667, 14.66667], "rotation": 90, "texture": "#0"},
				"south": {"uv": [10.66667, 14.33333, 11.66667, 14.66667], "texture": "#0"},
				"west": {"uv": [10.66667, 13.66667, 11, 14.66667], "rotation": 270, "texture": "#0"},
				"up": {"uv": [10.66667, 13.66667, 11.66667, 14.66667], "texture": "#0"},
				"down": {"uv": [10.66667, 14.66667, 11.66667, 13.66667], "texture": "#0"}
			}
		},
		{
			"name": "withercharm_76",
			"from": [3.66667, 7.83333, 11.83333],
			"to": [4, 8.16667, 12.16667],
			"rotation": {"angle": 0, "axis": "y", "origin": [0, 7.83333, -2.16667]},
			"faces": {
				"north": {"uv": [4, 14, 3.66667, 14.33333], "texture": "#0"},
				"east": {"uv": [3.66667, 14, 4, 14.33333], "rotation": 90, "texture": "#0"},
				"south": {"uv": [3.66667, 14, 4, 14.33333], "texture": "#0"},
				"west": {"uv": [3.66667, 14, 4, 14.33333], "rotation": 270, "texture": "#0"},
				"up": {"uv": [3.66667, 14, 4, 14.33333], "texture": "#0"},
				"down": {"uv": [3.66667, 14.33333, 4, 14], "texture": "#0"}
			}
		},
		{
			"name": "withercharm_77",
			"from": [6, 7.83333, 11.83333],
			"to": [6.66667, 8.16667, 12.16667],
			"rotation": {"angle": 0, "axis": "y", "origin": [0, 7.83333, -2.16667]},
			"faces": {
				"north": {"uv": [6.66667, 14, 6, 14.33333], "texture": "#0"},
				"east": {"uv": [6.33333, 14, 6.66667, 14.33333], "rotation": 90, "texture": "#0"},
				"south": {"uv": [6, 14, 6.66667, 14.33333], "texture": "#0"},
				"west": {"uv": [6, 14, 6.33333, 14.33333], "rotation": 270, "texture": "#0"},
				"up": {"uv": [6, 14, 6.66667, 14.33333], "texture": "#0"},
				"down": {"uv": [6, 14.33333, 6.66667, 14], "texture": "#0"}
			}
		},
		{
			"name": "withercharm_78",
			"from": [7, 7.83333, 11.83333],
			"to": [7.33333, 8.16667, 12.16667],
			"rotation": {"angle": 0, "axis": "y", "origin": [0, 7.83333, -2.16667]},
			"faces": {
				"north": {"uv": [7.33333, 14, 7, 14.33333], "texture": "#0"},
				"east": {"uv": [7, 14, 7.33333, 14.33333], "rotation": 90, "texture": "#0"},
				"south": {"uv": [7, 14, 7.33333, 14.33333], "texture": "#0"},
				"west": {"uv": [7, 14, 7.33333, 14.33333], "rotation": 270, "texture": "#0"},
				"up": {"uv": [7, 14, 7.33333, 14.33333], "texture": "#0"},
				"down": {"uv": [7, 14.33333, 7.33333, 14], "texture": "#0"}
			}
		},
		{
			"name": "withercharm_79",
			"from": [10.33333, 7.83333, 11.83333],
			"to": [10.66667, 8.16667, 12.5],
			"rotation": {"angle": 0, "axis": "y", "origin": [0, 7.83333, -2.16667]},
			"faces": {
				"north": {"uv": [10.66667, 14, 10.33333, 14.33333], "texture": "#0"},
				"east": {"uv": [10.33333, 14, 10.66667, 14.66667], "rotation": 90, "texture": "#0"},
				"south": {"uv": [10.33333, 14.33333, 10.66667, 14.66667], "texture": "#0"},
				"west": {"uv": [10.33333, 14, 10.66667, 14.66667], "rotation": 270, "texture": "#0"},
				"up": {"uv": [10.33333, 14, 10.66667, 14.66667], "texture": "#0"},
				"down": {"uv": [10.33333, 14.66667, 10.66667, 14], "texture": "#0"}
			}
		},
		{
			"name": "withercharm_80",
			"from": [11.66667, 7.83333, 11.83333],
			"to": [12, 8.16667, 12.16667],
			"rotation": {"angle": 0, "axis": "y", "origin": [0, 7.83333, -2.16667]},
			"faces": {
				"north": {"uv": [12, 14, 11.66667, 14.33333], "texture": "#0"},
				"east": {"uv": [11.66667, 14, 12, 14.33333], "rotation": 90, "texture": "#0"},
				"south": {"uv": [11.66667, 14, 12, 14.33333], "texture": "#0"},
				"west": {"uv": [11.66667, 14, 12, 14.33333], "rotation": 270, "texture": "#0"},
				"up": {"uv": [11.66667, 14, 12, 14.33333], "texture": "#0"},
				"down": {"uv": [11.66667, 14.33333, 12, 14], "texture": "#0"}
			}
		},
		{
			"name": "withercharm_81",
			"from": [4.33333, 7.83333, 12.16667],
			"to": [4.66667, 8.16667, 12.5],
			"rotation": {"angle": 0, "axis": "y", "origin": [0, 7.83333, -2.16667]},
			"faces": {
				"north": {"uv": [4.66667, 14.33333, 4.33333, 14.66667], "texture": "#0"},
				"east": {"uv": [4.33333, 14.33333, 4.66667, 14.66667], "rotation": 90, "texture": "#0"},
				"south": {"uv": [4.33333, 14.33333, 4.66667, 14.66667], "texture": "#0"},
				"west": {"uv": [4.33333, 14.33333, 4.66667, 14.66667], "rotation": 270, "texture": "#0"},
				"up": {"uv": [4.33333, 14.33333, 4.66667, 14.66667], "texture": "#0"},
				"down": {"uv": [4.33333, 14.66667, 4.66667, 14.33333], "texture": "#0"}
			}
		},
		{
			"name": "withercharm_82",
			"from": [5, 7.83333, 12.16667],
			"to": [6.33333, 8.16667, 13.16667],
			"rotation": {"angle": 0, "axis": "y", "origin": [0, 7.83333, -2.16667]},
			"faces": {
				"north": {"uv": [6.33333, 14.33333, 5, 14.66667], "texture": "#0"},
				"east": {"uv": [6, 14.33333, 6.33333, 15.33333], "rotation": 90, "texture": "#0"},
				"south": {"uv": [5, 15, 6.33333, 15.33333], "texture": "#0"},
				"west": {"uv": [5, 14.33333, 5.33333, 15.33333], "rotation": 270, "texture": "#0"},
				"up": {"uv": [5, 14.33333, 6.33333, 15.33333], "texture": "#0"},
				"down": {"uv": [5, 15.33333, 6.33333, 14.33333], "texture": "#0"}
			}
		},
		{
			"name": "withercharm_83",
			"from": [9.33333, 7.83333, 12.16667],
			"to": [10.33333, 8.16667, 12.83333],
			"rotation": {"angle": 0, "axis": "y", "origin": [0, 7.83333, -2.16667]},
			"faces": {
				"north": {"uv": [10.33333, 14.33333, 9.33333, 14.66667], "texture": "#0"},
				"east": {"uv": [10, 14.33333, 10.33333, 15], "rotation": 90, "texture": "#0"},
				"south": {"uv": [9.33333, 14.66667, 10.33333, 15], "texture": "#0"},
				"west": {"uv": [9.33333, 14.33333, 9.66667, 15], "rotation": 270, "texture": "#0"},
				"up": {"uv": [9.33333, 14.33333, 10.33333, 15], "texture": "#0"},
				"down": {"uv": [9.33333, 15, 10.33333, 14.33333], "texture": "#0"}
			}
		},
		{
			"name": "withercharm_84",
			"from": [9, 7.83333, 12.83333],
			"to": [9.33333, 8.16667, 13.16667],
			"rotation": {"angle": 0, "axis": "y", "origin": [0, 7.83333, -2.16667]},
			"faces": {
				"north": {"uv": [9.33333, 15, 9, 15.33333], "texture": "#0"},
				"east": {"uv": [9, 15, 9.33333, 15.33333], "rotation": 90, "texture": "#0"},
				"south": {"uv": [9, 15, 9.33333, 15.33333], "texture": "#0"},
				"west": {"uv": [9, 15, 9.33333, 15.33333], "rotation": 270, "texture": "#0"},
				"up": {"uv": [9, 15, 9.33333, 15.33333], "texture": "#0"},
				"down": {"uv": [9, 15.33333, 9.33333, 15], "texture": "#0"}
			}
		},
		{
			"name": "withercharm_85",
			"from": [5.33333, 7.83333, 13.16667],
			"to": [6.66667, 8.16667, 13.5],
			"rotation": {"angle": 0, "axis": "y", "origin": [0, 7.83333, -2.16667]},
			"faces": {
				"north": {"uv": [6.66667, 15.33333, 5.33333, 15.66667], "texture": "#0"},
				"east": {"uv": [6.33333, 15.33333, 6.66667, 15.66667], "rotation": 90, "texture": "#0"},
				"south": {"uv": [5.33333, 15.33333, 6.66667, 15.66667], "texture": "#0"},
				"west": {"uv": [5.33333, 15.33333, 5.66667, 15.66667], "rotation": 270, "texture": "#0"},
				"up": {"uv": [5.33333, 15.33333, 6.66667, 15.66667], "texture": "#0"},
				"down": {"uv": [5.33333, 15.66667, 6.66667, 15.33333], "texture": "#0"}
			}
		}
	],
	"gui_light": "front",
	"display": {
		"thirdperson_righthand": {
			"rotation": [79, 0, 0],
			"translation": [0.75, 2.25, 0.75],
			"scale": [0.25, 0.25, 0.25]
		},
		"thirdperson_lefthand": {
			"rotation": [79, 0, 0],
			"translation": [0.75, 2.25, 0.75],
			"scale": [0.25, 0.25, 0.25]
		},
		"firstperson_righthand": {
			"rotation": [100, 0, 73],
			"translation": [0, 4.25, 2.25],
			"scale": [0.39, 0.39, 0.39]
		},
		"firstperson_lefthand": {
			"rotation": [100, 0, 73],
			"translation": [0, 4.25, 2.25],
			"scale": [0.39, 0.39, 0.39]
		},
		"ground": {
			"rotation": [90, 0, 0],
			"translation": [0, 0.5, 0],
			"scale": [0.39, 0.39, 0.39]
		},
		"gui": {
			"rotation": [90, 0, 0],
			"translation": [0, -2.25, 0]
		},
		"fixed": {
			"rotation": [90, 0, 0],
			"translation": [0, -1.75, 0]
		}
	},
	"groups": [
		{
			"name": "withercharm",
			"origin": [8, 8, 8],
			"color": 0,
			"children": [
				0,
				1,
				2,
				3,
				4,
				5,
				6,
				7,
				8,
				9,
				10,
				11,
				12,
				13,
				14,
				15,
				16,
				17,
				18,
				19,
				20,
				21,
				22,
				23,
				24,
				25,
				26,
				27,
				28,
				29,
				30,
				31,
				32,
				33,
				34,
				35,
				36,
				37,
				38,
				39,
				40,
				41,
				42,
				43,
				44,
				45,
				46,
				47,
				48,
				49,
				50,
				51,
				52,
				53,
				54,
				55,
				56,
				57,
				58,
				59,
				60,
				61,
				62,
				63,
				64,
				65,
				66,
				67,
				68,
				69,
				70,
				71,
				72,
				73,
				74,
				75,
				76,
				77,
				78,
				79,
				80,
				81,
				82,
				83,
				84,
				85
			]
		}
	]
}